<?xml version="1.0" encoding="utf-8"?><HelpTOCNode Title="PointStack(TPoint) Methods" Url="html/E9479765.htm"><HelpTOCNode Title="IEnumerable.GetEnumerator Method " Url="html/94663C6B.htm" /><HelpTOCNode Title="Clear Method " Url="html/7757E148.htm" /><HelpTOCNode Title="Contains Method " Url="html/AA5E54B8.htm" /><HelpTOCNode Title="CopyTo Method " Url="html/77C1EF6A.htm" HasChildren="true" /><HelpTOCNode Title="GetEnumerator Method " Url="html/319475A3.htm" /><HelpTOCNode Title="Peek Method " Url="html/1DDE5341.htm" /><HelpTOCNode Title="Pop Method " Url="html/6B9EE210.htm" /><HelpTOCNode Title="Push Method " Url="html/5CAB102.htm" /><HelpTOCNode Title="ToArray Method " Url="html/BF3A88B9.htm" /><HelpTOCNode Title="TrimExcess Method " Url="html/6D3FE1D.htm" /></HelpTOCNode>