
{"items":[{"name":"Changes","href":"Changes.html","topicHref":"Changes.html"},{"name":"Samples","href":"Samples.html","topicHref":"Samples.html"},{"name":"Response Curves","href":"ResponseCurves.html","topicHref":"ResponseCurves.html"},{"name":"Generators","href":"Generators.html","topicHref":"Generators.html"},{"name":"Custom Pools","href":"custom_pools.html","topicHref":"custom_pools.html"},{"name":"Property Drawers","href":"PropertyDrawers.html","topicHref":"PropertyDrawers.html"}],"pdf":false}
